fds/__init__.py
fds/sdk/__init__.py
fds/sdk/FactSetPrivateCompany/__init__.py
fds/sdk/FactSetPrivateCompany/api_client.py
fds/sdk/FactSetPrivateCompany/configuration.py
fds/sdk/FactSetPrivateCompany/exceptions.py
fds/sdk/FactSetPrivateCompany/model_utils.py
fds/sdk/FactSetPrivateCompany/rest.py
fds/sdk/FactSetPrivateCompany/api/__init__.py
fds/sdk/FactSetPrivateCompany/api/company_reports_api.py
fds/sdk/FactSetPrivateCompany/api/financials_api.py
fds/sdk/FactSetPrivateCompany/api/metrics_api.py
fds/sdk/FactSetPrivateCompany/api/non_periodic_api.py
fds/sdk/FactSetPrivateCompany/api/universe_api.py
fds/sdk/FactSetPrivateCompany/apis/__init__.py
fds/sdk/FactSetPrivateCompany/model/__init__.py
fds/sdk/FactSetPrivateCompany/model/entity_match.py
fds/sdk/FactSetPrivateCompany/model/entity_match_request.py
fds/sdk/FactSetPrivateCompany/model/entity_match_request_body.py
fds/sdk/FactSetPrivateCompany/model/entity_matches_response.py
fds/sdk/FactSetPrivateCompany/model/error_object.py
fds/sdk/FactSetPrivateCompany/model/error_object_links.py
fds/sdk/FactSetPrivateCompany/model/error_response.py
fds/sdk/FactSetPrivateCompany/model/financial_statements.py
fds/sdk/FactSetPrivateCompany/model/financial_statements_response.py
fds/sdk/FactSetPrivateCompany/model/financials.py
fds/sdk/FactSetPrivateCompany/model/financials_metrics.py
fds/sdk/FactSetPrivateCompany/model/financials_request.py
fds/sdk/FactSetPrivateCompany/model/financials_request_body.py
fds/sdk/FactSetPrivateCompany/model/financials_response.py
fds/sdk/FactSetPrivateCompany/model/metric.py
fds/sdk/FactSetPrivateCompany/model/metrics_response.py
fds/sdk/FactSetPrivateCompany/model/non_periodic.py
fds/sdk/FactSetPrivateCompany/model/non_periodic_metrics.py
fds/sdk/FactSetPrivateCompany/model/non_periodic_request.py
fds/sdk/FactSetPrivateCompany/model/non_periodic_request_body.py
fds/sdk/FactSetPrivateCompany/model/non_periodic_response.py
fds/sdk/FactSetPrivateCompany/model/non_periodic_value.py
fds_sdk_factsetprivatecompany-1.0.1.dist-info/licenses/LICENSE
fds_sdk_factsetprivatecompany-1.0.1.dist-info/METADATA
fds_sdk_factsetprivatecompany-1.0.1.dist-info/WHEEL
fds_sdk_factsetprivatecompany-1.0.1.dist-info/top_level.txt
fds_sdk_factsetprivatecompany-1.0.1.dist-info/RECORD
